Metadata-Version: 2.1
Name: filters-package
Version: 0.5.6
Summary: um pacote que modifica imagens rgb para canais de imagens LUV, aplica os filtros gray, gaussiano, clahe, equalização de histograma e bordas de objetos nas imagens em uma determianda pasta com N imagens
Home-page: https://github.com/saul-rocha/FilterFS.git
Author: Saul Rocha
Author-email: saul.rocha2001@gmail.com
License: UNKNOWN
Project-URL: Bug Tracker, https://github.com/saul-rocha/FilterFS.git/issues
Platform: UNKNOWN
Classifier: Programming Language :: Python :: 3
Classifier: License :: OSI Approved :: MIT License
Classifier: Operating System :: OS Independent
Requires-Python: >=3.8
License-File: LICENSE
